culour/__init__.py
culour/culour.py
culour-0.3.dist-info/LICENSE
culour-0.3.dist-info/METADATA
culour-0.3.dist-info/WHEEL
culour-0.3.dist-info/top_level.txt
culour-0.3.dist-info/RECORD
