Metadata-Version: 2.1
Name: culour
Version: 0.3
Summary: Print colored strings in a curses window
Home-page: https://github.com/shohamp/culour
Download-URL: https://github.com/shohamp/culour/tarball/0.1
Author: Shoham Peller
Author-email: shohamp@gmail.com
Keywords: curses,color,colour
License-File: LICENSE
